polytope_python-2.0.0.dist-info/RECORD
polytope_python-2.0.0.dist-info/WHEEL
polytope_python-2.0.0.dist-info/top_level.txt
polytope_python-2.0.0.dist-info/METADATA
polytope_python-2.0.0.dist-info/licenses/LICENSE
polytope_feature/options.py
polytope_feature/polytope_rs.cpython-310-darwin.so
polytope_feature/shapes.py
polytope_feature/_version.py
polytope_feature/__init__.py
polytope_feature/polytope.py
polytope_feature/datacube/index_tree_pb2.py
polytope_feature/datacube/tensor_index_tree.py
polytope_feature/datacube/__init__.py
polytope_feature/datacube/index_tree.proto
polytope_feature/datacube/datacube_axis.py
polytope_feature/datacube/tree_encoding.py
polytope_feature/datacube/transformations/__init__.py
polytope_feature/datacube/transformations/datacube_transformations.py
polytope_feature/datacube/transformations/datacube_mappers/__init__.py
polytope_feature/datacube/transformations/datacube_mappers/datacube_mappers.py
polytope_feature/datacube/transformations/datacube_mappers/mapper_types/regular.py
polytope_feature/datacube/transformations/datacube_mappers/mapper_types/local_regular.py
polytope_feature/datacube/transformations/datacube_mappers/mapper_types/reduced_ll.py
polytope_feature/datacube/transformations/datacube_mappers/mapper_types/__init__.py
polytope_feature/datacube/transformations/datacube_mappers/mapper_types/healpix.py
polytope_feature/datacube/transformations/datacube_mappers/mapper_types/irregular.py
polytope_feature/datacube/transformations/datacube_mappers/mapper_types/octahedral.py
polytope_feature/datacube/transformations/datacube_mappers/mapper_types/healpix_nested.py
polytope_feature/datacube/transformations/datacube_mappers/mapper_types/reduced_gaussian.py
polytope_feature/datacube/transformations/datacube_mappers/mapper_types/irregular_mapper_types/icon.py
polytope_feature/datacube/transformations/datacube_mappers/mapper_types/irregular_mapper_types/lambert_conformal.py
polytope_feature/datacube/transformations/datacube_mappers/mapper_types/irregular_mapper_types/unstructured.py
polytope_feature/datacube/transformations/datacube_mappers/mapper_types/irregular_mapper_types/__init__.py
