Metadata-Version: 2.1
Name: polytope-python
Version: 2.0.0
Summary: Polytope datacube feature extraction library
Author-email: "European Centre for Medium-Range Weather Forecasts (ECMWF)" <software.support@ecmwf.int>
Maintainer-email: James Hawkes <James.Hawkes@ecmwf.int>, Mathilde Leuridan <Mathilde.Leuridan@ecmwf.int>
License: Apache License Version 2.0
Project-URL: repository, https://github.com/ecmwf/polytope
Project-URL: documentation, https://polytope.readthedocs.io/en/latest/
Project-URL: issues, https://github.com/ecmwf/polytope/issues
Classifier: Development Status :: 4 - Beta
Classifier: Intended Audience :: Science/Research
Classifier: Natural Language :: English
Classifier: License :: OSI Approved :: Apache Software License
Classifier: Operating System :: OS Independent
Classifier: Programming Language :: Python :: 3 :: Only
Classifier: Programming Language :: Python :: 3.8
Classifier: Programming Language :: Python :: 3.9
Classifier: Programming Language :: Python :: 3.10
Classifier: Programming Language :: Python :: 3.11
Classifier: Programming Language :: Python :: 3.12
Classifier: Topic :: Scientific/Engineering
Requires-Python: >3.8
License-File: LICENSE
Requires-Dist: numpy >=1.26
Requires-Dist: pandas
Requires-Dist: scipy
Requires-Dist: sortedcontainers
Requires-Dist: tripy
Requires-Dist: xarray
Requires-Dist: conflator
Requires-Dist: protobuf
Provides-Extra: tests
Requires-Dist: pytest ; extra == 'tests'
Requires-Dist: pytest-cov ; extra == 'tests'
Requires-Dist: cffi ; extra == 'tests'
Requires-Dist: eccodes ; extra == 'tests'
Requires-Dist: h5netcdf ; extra == 'tests'
Requires-Dist: h5py ; extra == 'tests'
Requires-Dist: earthkit-data ; extra == 'tests'
Requires-Dist: matplotlib ; extra == 'tests'
Requires-Dist: pyfdb ; extra == 'tests'
